glossing/__init__.py
glossing/bleu.py
glossing/eval.py
glossing/files.py
glossing/igt.py
glossing-1.0.4.dist-info/METADATA
glossing-1.0.4.dist-info/WHEEL
glossing-1.0.4.dist-info/licenses/LICENSE
glossing-1.0.4.dist-info/RECORD
