Metadata-Version: 2.4
Name: glossing
Version: 1.0.4
Summary: Python manipulation of interlinear glossed text
Project-URL: Homepage, https://github.com/michaelpginn/igt
Project-URL: Issues, https://github.com/michaelpginn/igt/issues
Author-email: Michael Ginn <michael.ginn@colorado.edu>
License-File: LICENSE
Classifier: License :: OSI Approved :: MIT License
Classifier: Operating System :: OS Independent
Classifier: Programming Language :: Python :: 3
Requires-Python: >=3.8
Provides-Extra: dev
Requires-Dist: build; extra == 'dev'
Requires-Dist: twine; extra == 'dev'
